phymlq/__init__.py
phymlq/ml/__init__.py
phymlq/ml/particle_net/__init__.py
phymlq/ml/particle_net/datasets.py
phymlq/ml/particle_net/layers.py
phymlq/ml/particle_net/models.py
phymlq/ml/particle_net/weights.py
phymlq-0.1.0.dist-info/LICENSE
phymlq-0.1.0.dist-info/METADATA
phymlq-0.1.0.dist-info/WHEEL
phymlq-0.1.0.dist-info/top_level.txt
phymlq-0.1.0.dist-info/RECORD
