Metadata-Version: 2.1
Name: phymlq
Version: 0.1.0
Summary: Helper Methods for several paper replications related to machine learning and quantum computation, physics oriented in particular.
Home-page: https://github.com/Jai2500/particle-tagging/
Author: Animesh Sinha, Jai Bardhan, Kalp Shah
Author-email: animesh.sinha@research.iiit.ac.in, jai.bardhan@research.iiit.ac.in, kalp.shah@research.iiit.ac.in
License: UNKNOWN
Platform: UNKNOWN
Classifier: Programming Language :: Python :: 3
Classifier: License :: OSI Approved :: MIT License
Classifier: Operating System :: OS Independent
Requires-Python: >=3.6
